neuma_client/__init__.py
neuma_client/auth.py
neuma_client/client.py
neuma_client/exceptions.py
neuma_client/pagination.py
neuma_client/proxies.py
neuma_client-0.2.0.dist-info/LICENSE
neuma_client-0.2.0.dist-info/METADATA
neuma_client-0.2.0.dist-info/WHEEL
neuma_client-0.2.0.dist-info/top_level.txt
neuma_client-0.2.0.dist-info/RECORD
